README.md
config.py.in
pyproject.toml
setup.cfg
setup.py
./CMakeLists.txt
./patches/Makefile.patch
./patches/comm.patch
lyncs_DDalphaAMG/__init__.py
lyncs_DDalphaAMG/config.py
lyncs_DDalphaAMG/lib.py
lyncs_DDalphaAMG/solver.py
lyncs_DDalphaAMG.egg-info/PKG-INFO
lyncs_DDalphaAMG.egg-info/SOURCES.txt
lyncs_DDalphaAMG.egg-info/dependency_links.txt
lyncs_DDalphaAMG.egg-info/requires.txt
lyncs_DDalphaAMG.egg-info/top_level.txt
test/__init__.py
test/test_benchmarks.py
test/test_solver.py