Metadata-Version: 2.1
Name: lyncs-DDalphaAMG
Version: 0.1.2
Summary: A Python interface to the DDalphaAMG multigrid solver library
Home-page: https://lyncs-api.github.io
Author: Simone Bacchio
Author-email: s.bacchio@gmail.com
License: UNKNOWN
Download-URL: https://github.com/Lyncs-API/lyncs.DDalphaAMG
Keywords: solver,library,interface,Python,multigrid,DDalphaAMG
Platform: UNKNOWN
Classifier: Development Status :: 2 - Pre-Alpha
Classifier: Intended Audience :: Developers
Classifier: Intended Audience :: Education
Classifier: Intended Audience :: Science/Research
Classifier: License :: OSI Approved :: BSD License
Classifier: Natural Language :: English
Classifier: Operating System :: Unix
Classifier: Programming Language :: C
Classifier: Programming Language :: C++
Classifier: Programming Language :: Python :: 3 :: Only
Classifier: Topic :: Scientific/Engineering :: Physics
Provides-Extra: test
Provides-Extra: all
